[
    {
      "id": "1",
      "title": "Remera Boxeador",
      "price": 2599,
      "category": "promociones",
      "description": "Remera de algodón talle único",
      "thumbnail": "Sin Imagen",
      "stock": 25
    },
    {
      "id": "2",
      "title": "Remera Gati Escondido",
      "price": 1999,
      "category": "promociones",
      "description": "Remera de algodón talle único",
      "thumbnail": "Sin Imagen",
      "stock": 98
    },
    {
      "id": "3",
      "title": "Remera Gentleman",
      "price": 1799,
      "category": "promociones",
      "description": "Remera de algodón talle XL",
      "thumbnail": "Sin Imagen",
      "stock": 54
    },
    {
      "id": "4",
      "title": "Gorra Glitter Rosa",
      "price": 999,
      "category": "promociones",
      "description": "Gorra con orejitas, ¡último color disponible!",
      "thumbnail": "Sin Imagen",
      "stock": 32
    },
    {
      "id": "5",
      "title": "Collar Silueta Gatito",
      "price": 1759,
      "category": "varios",
      "description": "Dije enchapado en plata. Disponible sin cadenita",
      "thumbnail": "Sin Imagen",
      "stock": 12
        },
    {
      "id": "6",
      "title": "AurisBlack",
      "price": 4329,
      "category": "varios",
      "description": "Auriculares con luz",
      "thumbnail": "Sin Imagen",
      "stock": 32
    },
    {
      "id": "7",
      "title": "Set de Lapiceras 'Huellita'",
      "price": 999,
      "category": "varios",
      "description": "Lapiceras surtidas trazo azul y negro",
      "thumbnail": "Sin Imagen",
      "stock": 546
    },
    {
      "id": "8",
      "title": "Medias",
      "price": 1050,
      "category": "varios",
      "description": "Medias surtidas",
      "thumbnail": "Sin Imagen",
      "stock": 45
        },
    {
      "id": "9",
      "title": "MoussePad",
      "price": 2099,
      "category": "varios",
      "description": "MoussePads de diferentes diseños!",
      "thumbnail": "Sin Imagen",
      "stock": 156
    },
    {
      "id": "10",
      "title": "Reloj Sueño del Árbol",
      "price": 3399,
      "category": "hogarydeco",
      "description": "Reloj pintado a mano",
      "thumbnail": "Sin Imagen",
      "stock": 56
    }
  ]